dcs_bios_connector/__init__.py
dcs_bios_connector/aircraft_json_parser.py
dcs_bios_connector/control_parser.py
dcs_bios_connector/dcs_bios_connector.py
dcs_bios_connector/event_constants.py
dcs_bios_connector/parser.py
dcs_bios_connector/udp_connector.py
dcs_bios_connector/json/A-10C.json
dcs_bios_connector/json/A-29B.json
dcs_bios_connector/json/A-4E-C.json
dcs_bios_connector/json/AH-64D.json
dcs_bios_connector/json/AH-6J.json
dcs_bios_connector/json/AJS37.json
dcs_bios_connector/json/AV8BNA.json
dcs_bios_connector/json/AircraftAliases.json
dcs_bios_connector/json/Alphajet.json
dcs_bios_connector/json/Bf-109K-4.json
dcs_bios_connector/json/C-101.json
dcs_bios_connector/json/Christen Eagle II.json
dcs_bios_connector/json/CommonData.json
dcs_bios_connector/json/Edge540.json
dcs_bios_connector/json/F-14.json
dcs_bios_connector/json/F-15E.json
dcs_bios_connector/json/F-16C_50.json
dcs_bios_connector/json/F-22A.json
dcs_bios_connector/json/F-4E.json
dcs_bios_connector/json/F-5E-3.json
dcs_bios_connector/json/F-86F Sabre.json
dcs_bios_connector/json/FA-18C_hornet.json
dcs_bios_connector/json/FC3.json
dcs_bios_connector/json/FW-190A8.json
dcs_bios_connector/json/FW-190D9.json
dcs_bios_connector/json/I-16.json
dcs_bios_connector/json/JF-17.json
dcs_bios_connector/json/Ka-50.json
dcs_bios_connector/json/L-39.json
dcs_bios_connector/json/M-2000C.json
dcs_bios_connector/json/MB-339.json
dcs_bios_connector/json/MH-60R.json
dcs_bios_connector/json/MetadataEnd.json
dcs_bios_connector/json/MetadataStart.json
dcs_bios_connector/json/Mi-24P.json
dcs_bios_connector/json/Mi-8MT.json
dcs_bios_connector/json/MiG-15bis.json
dcs_bios_connector/json/MiG-19P.json
dcs_bios_connector/json/MiG-21Bis.json
dcs_bios_connector/json/MirageF1.json
dcs_bios_connector/json/Mosquito.json
dcs_bios_connector/json/NS430.json
dcs_bios_connector/json/OH-58D.json
dcs_bios_connector/json/P-47D.json
dcs_bios_connector/json/P-51D.json
dcs_bios_connector/json/SA342.json
dcs_bios_connector-1.4.dist-info/METADATA
dcs_bios_connector-1.4.dist-info/WHEEL
dcs_bios_connector-1.4.dist-info/top_level.txt
dcs_bios_connector-1.4.dist-info/RECORD
