Metadata-Version: 2.1
Name: dcs_bios_connector
Version: 1.4
Summary: Allows easy access to dcs bios state and sending of commands
Home-page: https://github.com/papiplanes/dcs_bios_connector
Author: Papi Planes
Author-email: papiplanesfly@gmail.com
Classifier: Programming Language :: Python :: 3
Classifier: Operating System :: OS Independent
Requires-Python: >=3.6
